{
    "id": 0,
    "expId": 1,
    "name": "warrior Talents",
    "trees": [
        {
            "name": "Arms",
            "bgURL": "warrior-arms-bg.jpg",
            "talentList": [
                {
                    "name": "Deep Wounds",
                    "x": 3,
                    "y": 3,
                    "bgURL": "abilities/ability_backstab",
                    "maxRank": 3,
                    "description": "Your critical strikes cause the opponent to bleed, dealing v0% of your melee weapon's average damage over 12 sec.",
                    "values": {
                        "v0": 20
                    }
                },
                {
                    "name": "Sword Specialization",
                    "x": 4,
                    "y": 5,
                    "bgURL": "weapons/inv_sword_27",
                    "maxRank": 5,
                    "description": "Gives you a v0% chance to get an extra attack on the same target after dealing damage with your Sword.",
                    "values": {
                        "v0": 1
                    }
                },
                {
                    "name": "Improved Heroic Strike",
                    "x": 1,
                    "y": 1,
                    "bgURL": "abilities/ability_rogue_ambush",
                    "maxRank": 3,
                    "description": "Reduces the cost of your Heroic Strike ability by v0 rage point.",
                    "values": {
                        "v0": 1
                    }
                },
                {
                    "name": "Mace Specialization",
                    "x": 3,
                    "y": 5,
                    "bgURL": "weapons/inv_mace_01",
                    "maxRank": 5,
                    "description": "Gives your melee attacks a chance to stun your target for 3 sec and generate 7 rage when using a Mace."
                },
                {
                    "name": "Improved Charge",
                    "x": 1,
                    "y": 2,
                    "bgURL": "abilities/ability_warrior_charge",
                    "maxRank": 2,
                    "description": "Increases the amount of rage generated by your Charge ability by v0.",
                    "values": {
                        "v0": 3
                    }
                },
                {
                    "name": "Improved Rend",
                    "x": 3,
                    "y": 1,
                    "bgURL": "abilities/ability_gouge",
                    "maxRank": 3,
                    "description": "Increases the bleed damage done by your Rend ability by v0%.",
                    "values": {
                        "v0": 25
                    }
                },
                {
                    "name": "Improved Thunder Clap",
                    "x": 3,
                    "y": 2,
                    "bgURL": "abilities/ability_thunderclap",
                    "maxRank": 3,
                    "description": "Reduces the cost of your Thunder Clap ability by v0 rage point and increases the damage by v1% and the slowing effect by an additional v2%.",
                    "values": {
                        "v0": [
                            1,
                            2,
                            4
                        ],
                        "v1": [
                            40,
                            70,
                            100
                        ],
                        "v2": [
                            4,
                            7,
                            10
                        ]
                    }
                },
                {
                    "name": "Improved Hamstring",
                    "x": 3,
                    "y": 6,
                    "bgURL": "abilities/ability_shockwave",
                    "maxRank": 3,
                    "description": "Gives your Hamstring ability a v0% chance to immobilize the target for 5 sec.",
                    "values": {
                        "v0": 5
                    }
                },
                {
                    "name": "Deflection",
                    "x": 2,
                    "y": 1,
                    "bgURL": "abilities/ability_parry",
                    "maxRank": 5,
                    "description": "Increases your Parry chance by v0%.",
                    "values": {
                        "v0": 1
                    }
                },
                {
                    "name": "Improved Overpower",
                    "x": 1,
                    "y": 3,
                    "bgURL": "weapons/inv_sword_05",
                    "maxRank": 2,
                    "description": "Increases the critical strike chance of your Overpower ability by v0%.",
                    "values": {
                        "v0": 25
                    }
                },
                {
                    "name": "Poleaxe Specialization",
                    "x": 1,
                    "y": 5,
                    "bgURL": "weapons/inv_axe_06",
                    "maxRank": 5,
                    "description": "Increases your chance to get a critical strike with Axes and Polearms by v0%.",
                    "values": {
                        "v0": 1
                    }
                },
                {
                    "name": "Death Wish",
                    "x": 2,
                    "y": 5,
                    "bgURL": "spells/spell_shadow_deathpact",
                    "maxRank": 1,
                    "description": "When activated, increases your physical damage by 20% and makes you immune to Fear effects, but increases all damage taken by 5%. Lasts 30 sec."
                },
                {
                    "name": "Improved Intercept",
                    "x": 1,
                    "y": 6,
                    "bgURL": "abilities/ability_rogue_sprint",
                    "maxRank": 2,
                    "description": "Reduces the cooldown of your Intercept ability by v0 sec.",
                    "values": {
                        "v0": 5
                    }
                },
                {
                    "name": "Mortal Strike",
                    "x": 2,
                    "y": 7,
                    "bgURL": "abilities/ability_warrior_savageblow",
                    "maxRank": 1,
                    "description": "A vicious strike that deals weapon damage plus 85 and wounds the target, reducing the effectiveness of any healing by 50% for 10 sec.",
                    "dependencyName": "Death Wish"
                },
                {
                    "name": "Two-Handed Weapon Specialization",
                    "x": 2,
                    "y": 4,
                    "bgURL": "weapons/inv_axe_09",
                    "maxRank": 5,
                    "description": "Increases the damage you deal with two-handed melee weapons by v0%.",
                    "values": {
                        "v0": 1
                    }
                },
                {
                    "name": "Anger Management",
                    "x": 2,
                    "y": 3,
                    "bgURL": "spells/spell_holy_blessingofstamina",
                    "maxRank": 1,
                    "description": "Generates 1 rage per 3 seconds while in combat."
                },
                {
                    "name": "Iron Will",
                    "x": 2,
                    "y": 2,
                    "bgURL": "spells/spell_magic_magearmor",
                    "maxRank": 5,
                    "description": "Increases your chance to resist stun and charm effects by v0%.",
                    "values": {
                        "v0": 3
                    }
                },
                {
                    "name": "Impale",
                    "x": 3,
                    "y": 4,
                    "bgURL": "abilities/ability_searingarrow",
                    "maxRank": 2,
                    "description": "Increases the critical strike damage bonus of your abilities in Battle, Defensive, and Berserker stance by v0%.",
                    "values": {
                        "v0": 10
                    },
                    "dependencyName": "Deep Wounds"
                },
                {
                    "name": "Improved Disciplines",
                    "x": 4,
                    "y": 6,
                    "bgURL": "abilities/ability_warrior_improveddisciplines",
                    "maxRank": 3,
                    "description": "Reduces the cooldown of your Retaliation, Recklessness and Shield Wall abilities by v0 min and increases their duration by v1 sec.",
                    "values": {
                        "v0": [
                            4,
                            7,
                            10
                        ],
                        "v1": 2
                    }
                },
                {
                    "name": "Blood Frenzy",
                    "x": 1,
                    "y": 7,
                    "bgURL": "abilities/ability_warrior_bloodfrenzy",
                    "maxRank": 2,
                    "description": "Your Rend and Deep Wounds abilities also increase all melee damage caused to that target by v0%.",
                    "values": {
                        "v0": 2
                    }
                },
                {
                    "name": "Second Wind",
                    "x": 3,
                    "y": 7,
                    "bgURL": "abilities/ability_hunter_harass",
                    "maxRank": 2,
                    "description": "Whenever you are struck by a Stun or Immobilize effect you will generate v0 rage and v1% of your total health over 10 sec.",
                    "values": {
                        "v0": 10,
                        "v1": 5
                    }
                },
                {
                    "name": "Improved Mortal Strike",
                    "x": 2,
                    "y": 8,
                    "bgURL": "abilities/ability_warrior_savageblow",
                    "maxRank": 5,
                    "description": "Reduces the cooldown of your Mortal Strike ability by v0 sec and increases the damage it causes by v1%.",
                    "values": {
                        "v0": [
                            0.2,
                            0.4,
                            0.6,
                            0.8,
                            1
                        ],
                        "v1": 1
                    },
                    "dependencyName": "Mortal Strike"
                },
                {
                    "name": "Endless Rage",
                    "x": 2,
                    "y": 9,
                    "bgURL": "abilities/ability_warrior_endlessrage",
                    "maxRank": 1,
                    "description": "You generate 25% more rage from damage dealt."
                }
            ]
        },
        {
            "name": "Fury",
            "bgURL": "warrior-fury-bg.jpg",
            "talentList": [
                {
                    "name": "Commanding Presence",
                    "x": 4,
                    "y": 3,
                    "bgURL": "spells/spell_nature_focusedmind",
                    "maxRank": 5,
                    "description": "Increases the melee attack power bonus of your Battle Shout and the health bonus of your Commanding Shout by v0%.",
                    "values": {
                        "v0": 5
                    }
                },
                {
                    "name": "Enrage",
                    "x": 3,
                    "y": 4,
                    "bgURL": "spells/spell_shadow_unholyfrenzy",
                    "maxRank": 5,
                    "description": "Gives you a v0% melee damage bonus for 12 sec up to a maximum of 12 swings after being the victim of a critical strike.",
                    "values": {
                        "v0": 5
                    }
                },
                {
                    "name": "Flurry",
                    "x": 3,
                    "y": 6,
                    "bgURL": "abilities/ability_ghoulfrenzy",
                    "maxRank": 5,
                    "description": "Increases your attack speed by v0% for your next 3 swings after dealing a melee critical strike.",
                    "values": {
                        "v0": 5
                    },
                    "dependencyName": "Enrage"
                },
                {
                    "name": "Cruelty",
                    "x": 3,
                    "y": 1,
                    "bgURL": "abilities/ability_rogue_eviscerate",
                    "maxRank": 5,
                    "description": "Increases your chance to get a critical strike with melee weapons by v0%.",
                    "values": {
                        "v0": 1
                    }
                },
                {
                    "name": "Booming Voice",
                    "x": 2,
                    "y": 1,
                    "bgURL": "spells/spell_nature_purge",
                    "maxRank": 5,
                    "description": "Increases the area of effect and duration of your Battle Shout, Demoralizing Shout, and Commanding Shout by v0%.",
                    "values": {
                        "v0": 10
                    }
                },
                {
                    "name": "Unbridled Wrath",
                    "x": 3,
                    "y": 2,
                    "bgURL": "spells/spell_nature_stoneclawtotem",
                    "maxRank": 5,
                    "description": "Gives you a chance to generate an additional rage point when you deal melee damage with a weapon."
                },
                {
                    "name": "Piercing Howl",
                    "x": 2,
                    "y": 3,
                    "bgURL": "spells/spell_shadow_deathscream",
                    "maxRank": 1,
                    "description": "Causes all enemies near the warrior to be dazed, reducing movement speed by 50% for 6 sec."
                },
                {
                    "name": "Improved Demoralizing Shout",
                    "x": 2,
                    "y": 2,
                    "bgURL": "abilities/ability_warrior_warcry",
                    "maxRank": 5,
                    "description": "Increases the melee attack power reduction of your Demoralizing Shout by v0%.",
                    "values": {
                        "v0": 8
                    }
                },
                {
                    "name": "Sweeping Strikes",
                    "x": 2,
                    "y": 5,
                    "bgURL": "abilities/ability_rogue_slicedice",
                    "maxRank": 1,
                    "description": "Your next 10 melee weapon swings strike an additional nearby opponent."
                },
                {
                    "name": "Improved Cleave",
                    "x": 1,
                    "y": 3,
                    "bgURL": "abilities/ability_warrior_cleave",
                    "maxRank": 3,
                    "description": "Increases the bonus damage done by your Cleave ability by v0%.",
                    "values": {
                        "v0": 40
                    }
                },
                {
                    "name": "Bloodthirst",
                    "x": 2,
                    "y": 7,
                    "bgURL": "spells/spell_nature_bloodlust",
                    "maxRank": 1,
                    "description": "Instantly attack the target causing 511 damage. In addition, the next 5 successful melee attacks will restore 10 health. This effect lasts 8 sec. Damage is based on your attack power.",
                    "dependencyName": "Sweeping Strikes"
                },
                {
                    "name": "Improved Slam",
                    "x": 1,
                    "y": 5,
                    "bgURL": "abilities/ability_warrior_decisivestrike",
                    "maxRank": 2,
                    "description": "Decreases the casting time of your Slam ability by v0 sec.",
                    "values": {
                        "v0": 0.5
                    }
                },
                {
                    "name": "Blood Craze",
                    "x": 3,
                    "y": 3,
                    "bgURL": "spells/spell_shadow_summonimp",
                    "maxRank": 3,
                    "description": "Regenerates v0% of your total health over 6 sec after being the victim of a critical strike.",
                    "values": {
                        "v0": 1
                    }
                },
                {
                    "name": "Improved Berserker Rage",
                    "x": 1,
                    "y": 6,
                    "bgURL": "spells/spell_nature_ancestralguardian",
                    "maxRank": 2,
                    "description": "The Berserker Rage ability will generate v0 rage when used.",
                    "values": {
                        "v0": 5
                    }
                },
                {
                    "name": "Improved Execute",
                    "x": 2,
                    "y": 4,
                    "bgURL": "weapons/inv_sword_48",
                    "maxRank": 2,
                    "description": "Reduces the Rage cost of your Execute ability by v0.",
                    "values": {
                        "v0": [
                            2,
                            5
                        ]
                    }
                },
                {
                    "name": "Weapon Mastery",
                    "x": 4,
                    "y": 5,
                    "bgURL": "abilities/ability_warrior_weaponmastery",
                    "maxRank": 2,
                    "description": "Reduces the chance for you attacks to be dodged by v0% and reduces the duration of all Disarm effects used against you by v1%. This does not stack with other Disarm duration reducing effects.",
                    "values": {
                        "v0": 1,
                        "v1": 25
                    }
                },
                {
                    "name": "Dual Wield Specialization",
                    "x": 1,
                    "y": 4,
                    "bgURL": "abilities/ability_dualwield",
                    "maxRank": 5,
                    "description": "Increases the damage done by your offhand weapon by v0%.",
                    "values": {
                        "v0": 5
                    }
                },
                {
                    "name": "Precision",
                    "x": 1,
                    "y": 7,
                    "bgURL": "abilities/ability_marksmanship",
                    "maxRank": 3,
                    "description": "Increases your chance to hit with melee weapons by v0%.",
                    "values": {
                        "v0": 1
                    }
                },
                {
                    "name": "Improved Whirlwind",
                    "x": 3,
                    "y": 7,
                    "bgURL": "abilities/ability_whirlwind",
                    "maxRank": 2,
                    "description": "Reduces the cooldown of your Whirlwind ability by v0 sec.",
                    "values": {
                        "v0": 1
                    }
                },
                {
                    "name": "Improved Berserker Stance",
                    "x": 3,
                    "y": 8,
                    "bgURL": "abilities/ability_racial_avatar",
                    "maxRank": 5,
                    "description": "Increases attack power by v0% and reduces threat caused by v1% while in Berserker Stance.",
                    "values": {
                        "v0": 2,
                        "v1": 2
                    }
                },
                {
                    "name": "Rampage",
                    "x": 2,
                    "y": 9,
                    "bgURL": "abilities/ability_warrior_rampage",
                    "maxRank": 1,
                    "description": "Warrior goes on a rampage, increasing attack power by 30 and causing most successful melee attacks to increase attack power by an additional 30. This effect will stack up to 5 times. Lasts 30 sec. This ability can only be used after scoring a critical hit.",
                    "dependencyName": "Bloodthirst"
                }
            ]
        },
        {
            "name": "Protection",
            "bgURL": "warrior-protection-bg.jpg",
            "talentList": [
                {
                    "name": "Anticipation",
                    "x": 3,
                    "y": 1,
                    "bgURL": "spells/spell_nature_mirrorimage",
                    "maxRank": 5,
                    "description": "Increases your Defense skill by v0.",
                    "values": {
                        "v0": 4
                    }
                },
                {
                    "name": "Toughness",
                    "x": 3,
                    "y": 2,
                    "bgURL": "spells/spell_holy_devotion",
                    "maxRank": 5,
                    "description": "Increases your armor value from items by v0%.",
                    "values": {
                        "v0": 2
                    }
                },
                {
                    "name": "Tactical Mastery",
                    "x": 2,
                    "y": 1,
                    "bgURL": "spells/spell_nature_enchantarmor",
                    "maxRank": 3,
                    "description": "You retain up to an additional v0 of your rage points when you change stances. Also greatly increases the threat generated by your Bloodthirst and Mortal Strike abilities when you are in Defensive Stance.",
                    "values": {
                        "v0": 5
                    }
                },
                {
                    "name": "Improved Bloodrage",
                    "x": 1,
                    "y": 1,
                    "bgURL": "abilities/ability_racial_bloodrage",
                    "maxRank": 2,
                    "description": "Increases the instant rage generated by your Bloodrage ability by v0.",
                    "values": {
                        "v0": 3
                    }
                },
                {
                    "name": "Improved Taunt",
                    "x": 3,
                    "y": 4,
                    "bgURL": "spells/spell_nature_reincarnation",
                    "maxRank": 2,
                    "description": "Reduces the cooldown of your Taunt ability by v0 sec.",
                    "values": {
                        "v0": 1
                    }
                },
                {
                    "name": "Defiance",
                    "x": 4,
                    "y": 3,
                    "bgURL": "abilities/ability_warrior_innerrage",
                    "maxRank": 3,
                    "description": "Increases the threat generated by your attacks by v0% while in Defensive Stance and increases your expertise by v1.",
                    "values": {
                        "v0": 5,
                        "v1": 2
                    }
                },
                {
                    "name": "Improved Shield Block",
                    "x": 2,
                    "y": 3,
                    "bgURL": "abilities/ability_defend",
                    "maxRank": 1,
                    "description": "Allows your Shield Block ability to block an additional attack, and increases the duration by 1 sec.",
                    "dependencyName": "Shield Specialization"
                },
                {
                    "name": "Improved Sunder Armor",
                    "x": 1,
                    "y": 4,
                    "bgURL": "abilities/ability_warrior_sunder",
                    "maxRank": 3,
                    "description": "Reduces the cost of your Sunder Armor and Devastate abilities by v0 rage point.",
                    "values": {
                        "v0": 1
                    }
                },
                {
                    "name": "Improved Revenge",
                    "x": 3,
                    "y": 3,
                    "bgURL": "abilities/ability_warrior_revenge",
                    "maxRank": 3,
                    "description": "Gives your Revenge ability a v0% chance to stun the target for 3 sec.",
                    "values": {
                        "v0": 15
                    }
                },
                {
                    "name": "Shield Slam",
                    "x": 2,
                    "y": 7,
                    "bgURL": "armor/inv_shield_05",
                    "maxRank": 1,
                    "description": "Slam the target with your shield, causing 225 to 235 damage, modified by your shield bloc value, and dispels 1 magic effect on the target. Also causes a high amount of threat.",
                    "dependencyName": "Concussion Blow"
                },
                {
                    "name": "Improved Shield Bash",
                    "x": 3,
                    "y": 5,
                    "bgURL": "abilities/ability_warrior_shieldbash",
                    "maxRank": 2,
                    "description": "Gives your Shield Bash ability a v0% chance to silence the target for 3 sec.",
                    "values": {
                        "v0": 50
                    }
                },
                {
                    "name": "Improved Shield Wall",
                    "x": 1,
                    "y": 5,
                    "bgURL": "abilities/ability_warrior_shieldwall",
                    "maxRank": 2,
                    "description": "Increases the effect duration of your Shield Wall ability by v0 secs.",
                    "values": {
                        "v0": [
                            3,
                            5
                        ]
                    }
                },
                {
                    "name": "Improved Disarm",
                    "x": 2,
                    "y": 4,
                    "bgURL": "abilities/ability_warrior_disarm",
                    "maxRank": 3,
                    "description": "Increases the duration of your Disarm ability by v0 secs.",
                    "values": {
                        "v0": 1
                    }
                },
                {
                    "name": "Concussion Blow",
                    "x": 2,
                    "y": 5,
                    "bgURL": "abilities/ability_thunderbolt",
                    "maxRank": 1,
                    "description": "Stuns the opponent for 5 sec."
                },
                {
                    "name": "Last Stand",
                    "x": 1,
                    "y": 3,
                    "bgURL": "spells/spell_holy_ashestoashes",
                    "maxRank": 1,
                    "description": "When activated, this ability temporarily grants you 30% of your maximum hit points for 20 sec. After the effect expires, the hit points are lost."
                },
                {
                    "name": "One-Handed Weapon Specialization",
                    "x": 3,
                    "y": 6,
                    "bgURL": "weapons/inv_sword_20",
                    "maxRank": 5,
                    "description": "Increases the damage you deal with One-Handed Melee weapons by v0%.",
                    "values": {
                        "v0": 2
                    }
                },
                {
                    "name": "Shield Specialization",
                    "x": 2,
                    "y": 2,
                    "bgURL": "armor/inv_shield_06",
                    "maxRank": 5,
                    "description": "Increases your chance to block attacks with a shield by v0% and has a v1% chance to generate 1 rage when a block occurs.",
                    "values": {
                        "v0": 1,
                        "v1": 20
                    }
                },
                {
                    "name": "Shield Mastery",
                    "x": 1,
                    "y": 6,
                    "bgURL": "abilities/ability_warrior_shieldmastery",
                    "maxRank": 3,
                    "description": "Increases the amount of damage absorbed by your shield by v0%.",
                    "values": {
                        "v0": 10
                    }
                },
                {
                    "name": "Improved Defensive Stance",
                    "x": 1,
                    "y": 7,
                    "bgURL": "abilities/ability_warrior_defensivestance",
                    "maxRank": 3,
                    "description": "Reduces all spell damage taken while in Defensive Stance by v0%.",
                    "values": {
                        "v0": 2
                    }
                },
                {
                    "name": "Focused Rage",
                    "x": 3,
                    "y": 7,
                    "bgURL": "abilities/ability_warrior_focusedrage",
                    "maxRank": 3,
                    "description": "Reduces the rage cost of your offensive abilities by v0.",
                    "values": {
                        "v0": 1
                    }
                },
                {
                    "name": "Vitality",
                    "x": 2,
                    "y": 8,
                    "bgURL": "armor/inv_helmet_21",
                    "maxRank": 5,
                    "description": "Increases your total Stamina by v0% and your total Strength by v1%.",
                    "values": {
                        "v0": 1,
                        "v1": 2
                    }
                },
                {
                    "name": "Devastate",
                    "x": 2,
                    "y": 9,
                    "bgURL": "weapons/inv_sword_11",
                    "maxRank": 1,
                    "description": "Sunder the target's armor causing the Sunder Armor effect. In addition, causes 50% of weapon damage plus 15 for each application of Sunder Armor on the target. The Sunder Armor effect can stack up to 5 times."
                }
            ]
        }
    ]
}